AUTHORS.md
CONTRIBUTING.md
HISTORY.md
LICENSE
MANIFEST.in
README.md
setup.cfg
setup.py
django_cache_manager/__init__.py
django_cache_manager/cache_manager.py
django_cache_manager/mixins.py
django_cache_manager/models.py
django_cache_manager/model_cache_sharing/__init__.py
django_cache_manager/model_cache_sharing/types.py
django_cache_manager/model_cache_sharing/backends/__init__.py
django_cache_manager/model_cache_sharing/backends/base.py
django_cache_manager/model_cache_sharing/backends/ipc.py
django_cache_manager/model_cache_sharing/backends/shared_memory.py
django_cache_manager_redux.egg-info/PKG-INFO
django_cache_manager_redux.egg-info/SOURCES.txt
django_cache_manager_redux.egg-info/dependency_links.txt
django_cache_manager_redux.egg-info/not-zip-safe
django_cache_manager_redux.egg-info/requires.txt
django_cache_manager_redux.egg-info/top_level.txt
tests/__init__.py
tests/cache_manager_tests.py
tests/factories.py
tests/m2m_tests.py
tests/manage.py
tests/mixin_tests.py
tests/model_integration_tests.py
tests/models.py
tests/settings.py
tests/shared_memory_tests.py
tests/shell.py
tests/signal_tests.py